socratagr/__init__.py
socratagr/grsocrata.py
socratagr/main.py
socratagr/socratagr.py
socratagr-0.0.1.dist-info/LICENSE
socratagr-0.0.1.dist-info/METADATA
socratagr-0.0.1.dist-info/WHEEL
socratagr-0.0.1.dist-info/top_level.txt
socratagr-0.0.1.dist-info/RECORD
