Metadata-Version: 2.1
Name: socratagr
Version: 0.0.1
Summary: Package to create, update, and delete data from The City of Grand Rapids instance of Socrata
Home-page: https://github.com/GRInnovation/socrata_package
Author: Example Author
Author-email: digitalservices@grcity.us
License: UNKNOWN
Platform: UNKNOWN
Classifier: Programming Language :: Python :: 3
Classifier: License :: OSI Approved :: MIT License
Classifier: Operating System :: OS Independent
Requires-Python: >=3.6
